{"stat.pickup.minecraft.bone":2,"stat.pickup.minecraft.wooden_slab":15,"stat.pickup.minecraft.stone_pressure_plate":1,"stat.leaveGame":2,"stat.mineBlock.minecraft.cobblestone":3,"stat.useItem.minecraft.diamond_sword":39,"stat.craftItem.minecraft.diamond_helmet":1,"stat.swimOneCm":3013,"stat.useItem.minecraft.planks":83,"stat.mineBlock.minecraft.spruce_stairs":13,"stat.drop.minecraft.cobblestone":3,"stat.useItem.minecraft.dirt":152,"stat.pickup.minecraft.bow":2,"stat.pickup.minecraft.rotten_flesh":2,"stat.craftItem.minecraft.iron_boots":1,"stat.pickup.minecraft.cobblestone":63,"stat.mineBlock.minecraft.wooden_slab":15,"stat.craftItem.minecraft.bow":1,"stat.flyOneCm":100928,"stat.killEntity.Witch":1,"stat.useItem.minecraft.cooked_beef":9,"stat.craftItem.minecraft.wooden_slab":6,"stat.timeSinceDeath":60015,"stat.drop.minecraft.diamond":13,"stat.drop.minecraft.log":111,"stat.useItem.minecraft.sign":1,"stat.craftItem.minecraft.wooden_pickaxe":1,"stat.useItem.minecraft.wooden_slab":15,"stat.drop.minecraft.coal":28,"stat.craftItem.minecraft.bed":1,"stat.craftItem.minecraft.stonebrick":64,"stat.pickup.minecraft.stonebrick":192,"stat.furnaceInteraction":71,"stat.drop.minecraft.dirt":64,"stat.mineBlock.minecraft.coal_ore":5,"stat.killEntity.Creeper":1,"stat.pickup.minecraft.string":1,"stat.pickup.minecraft.furnace":3,"stat.entityKilledBy.Skeleton":2,"stat.sprintOneCm":123489,"stat.useItem.minecraft.diamond_shovel":326,"stat.craftItem.minecraft.stick":20,"stat.useItem.minecraft.bed":1,"stat.craftItem.minecraft.stone":47,"stat.mineBlock.minecraft.crafting_table":1,"stat.useItem.minecraft.diamond_pickaxe":146,"stat.drop.minecraft.golden_apple":5,"stat.pickup.minecraft.emerald":1,"stat.pickup.minecraft.sugar":2,"stat.deaths":4,"stat.mineBlock.minecraft.planks":20,"stat.drop":24,"stat.playOneMinute":85578,"stat.useItem.minecraft.wooden_sword":11,"stat.craftItem.minecraft.diamond_pickaxe":1,"stat.killEntity.Zombie":6,"stat.drop.minecraft.torch":20,"stat.drop.minecraft.iron_ingot":2,"stat.craftItem.minecraft.diamond_axe":1,"stat.mineBlock.minecraft.tallgrass":5,"stat.diveOneCm":554,"stat.chestOpened":32,"stat.pickup.minecraft.sign":2,"stat.pickup.minecraft.arrow":3,"stat.drop.minecraft.cooked_beef":32,"stat.useItem.minecraft.diamond_axe":183,"stat.craftItem.minecraft.coal":4,"stat.pickup.minecraft.stone_brick_stairs":2,"stat.craftItem.minecraft.diamond_sword":1,"stat.jump":914,"stat.pickup.minecraft.coal":99,"stat.fallOneCm":13249,"stat.pickup.minecraft.iron_ingot":5,"stat.crouchOneCm":17689,"stat.pickup.minecraft.spider_eye":1,"stat.craftItem.minecraft.torch":20,"stat.craftItem.minecraft.iron_ingot":88,"stat.craftItem.minecraft.chest":1,"stat.pickup.minecraft.dirt":335,"stat.craftingTableInteraction":26,"stat.pickup.minecraft.iron_ore":34,"stat.useItem.minecraft.sapling":1,"stat.pickup.minecraft.wooden_pickaxe":1,"stat.damageTaken":1712,"stat.mineBlock.minecraft.torch":13,"stat.mineBlock.minecraft.furnace":3,"stat.useItem.minecraft.furnace":1,"stat.craftItem.minecraft.wooden_sword":1,"stat.pickup.minecraft.planks":85,"stat.craftItem.minecraft.diamond_shovel":1,"stat.craftItem.minecraft.iron_leggings":1,"stat.damageDealt":2219,"stat.useItem.minecraft.crafting_table":2,"stat.mineBlock.minecraft.dirt":329,"stat.walkOneCm":374546,"stat.useItem.minecraft.torch":9,"stat.pickup.minecraft.golden_apple":24,"stat.useItem.minecraft.chest":1,"stat.pickup.minecraft.stick":6,"stat.drop.minecraft.stone_brick_stairs":2,"stat.drop.minecraft.rotten_flesh":1,"stat.pickup.minecraft.crafting_table":3,"stat.useItem.minecraft.log":1,"stat.useItem.minecraft.cobblestone":54,"stat.craftItem.minecraft.crafting_table":1,"stat.pickup.minecraft.log":166,"stat.drop.minecraft.stonebrick":64,"stat.drop.minecraft.iron_ore":23,"stat.drop.minecraft.planks":15,"stat.pickup.minecraft.stone":5,"stat.useItem.minecraft.spruce_stairs":55,"stat.craftItem.minecraft.iron_chestplate":1,"stat.pickup.minecraft.sapling":7,"stat.pickup.minecraft.cooked_beef":96,"stat.killEntity.Skeleton":4,"stat.drop.minecraft.bow":2,"stat.mineBlock.minecraft.stonebrick":129,"stat.craftItem.minecraft.planks":96,"stat.mobKills":12,"stat.useItem.minecraft.stonebrick":164,"stat.mineBlock.minecraft.log":130,"stat.useItem.minecraft.spruce_door":2,"stat.pickup.minecraft.diamond":27,"stat.mineBlock.minecraft.leaves":18,"stat.pickup.minecraft.torch":33,"stat.pickup.minecraft.spruce_stairs":13,"stat.sneakTime":4433,"stat.craftItem.minecraft.spruce_stairs":52,"stat.mineBlock.minecraft.stone":6,"stat.craftItem.minecraft.spruce_door":3}